mcpo_control_panel/__main__.py
mcpo_control_panel/main.py
mcpo_control_panel/api/mcpo_control.py
mcpo_control_panel/api/server_crud.py
mcpo_control_panel/db/database.py
mcpo_control_panel/models/mcpo_settings.py
mcpo_control_panel/models/server_definition.py
mcpo_control_panel/services/config_service_old.py
mcpo_control_panel/services/mcpo_service.py
mcpo_control_panel/services/config_service/__init__.py
mcpo_control_panel/services/config_service/definition_manager.py
mcpo_control_panel/services/config_service/file_generator.py
mcpo_control_panel/services/config_service/settings_manager.py
mcpo_control_panel/ui/routes_old.py
mcpo_control_panel/ui/routes/__init__.py
mcpo_control_panel/ui/routes/main_ui_routes.py
mcpo_control_panel/ui/routes/routes.py
mcpo_control_panel/ui/routes/settings_routes.py
mcpo_control_panel/ui/static/css/style.css
mcpo_control_panel/ui/static/css/vendor/materialize.min.css
mcpo_control_panel/ui/static/fonts/flUhRq6tzZclQEJ-Vdg-IuiaDsNZ.ttf
mcpo_control_panel/ui/static/fonts/material-icons.css
mcpo_control_panel/ui/static/js/main.js
mcpo_control_panel/ui/static/js/vendor/htmx.min.js
mcpo_control_panel/ui/static/js/vendor/materialize.min.js
mcpo_control_panel/ui/templates/_bulk_add_preview.html
mcpo_control_panel/ui/templates/_mcpo_status.html
mcpo_control_panel/ui/templates/_server_form_macro.html
mcpo_control_panel/ui/templates/_server_row.html
mcpo_control_panel/ui/templates/add_servers_page.html
mcpo_control_panel/ui/templates/base.html
mcpo_control_panel/ui/templates/bulk_add_form.html
mcpo_control_panel/ui/templates/edit_server_page.html
mcpo_control_panel/ui/templates/index.html
mcpo_control_panel/ui/templates/logs.html
mcpo_control_panel/ui/templates/mcpo_settings_form.html
mcpo_control_panel/ui/templates/server_form.html
mcpo_control_panel/ui/templates/tools.html
mcpo_control_panel-0.1.6.dist-info/METADATA
mcpo_control_panel-0.1.6.dist-info/WHEEL
mcpo_control_panel-0.1.6.dist-info/top_level.txt
mcpo_control_panel-0.1.6.dist-info/RECORD
